[
  {
    "full_name": "ojigs/engagetrk",
    "stargazers_count": 1,
    "open_issues_count": 0,
    "forks_count": 0
  },
  {
    "full_name": "yeojz/otplib",
    "stargazers_count": 1753,
    "open_issues_count": 82,
    "forks_count": 122
  },
  {
    "full_name": "jollyjerr/react-autosave",
    "stargazers_count": 46,
    "open_issues_count": 1,
    "forks_count": 0
  },
  {
    "full_name": "samerbuna/efficient-node",
    "stargazers_count": 614,
    "open_issues_count": 1,
    "forks_count": 131
  },
  {
    "full_name": "kamranahmedse/design-patterns-for-humans",
    "stargazers_count": 42320,
    "open_issues_count": 11,
    "forks_count": 5009
  },
  {
    "full_name": "rauchg/how-is-this-not-illegal",
    "stargazers_count": 522,
    "open_issues_count": 5,
    "forks_count": 18
  },
  {
    "full_name": "Lihemen/furbar",
    "stargazers_count": 1,
    "open_issues_count": 0,
    "forks_count": 0
  },
  {
    "full_name": "yoavbls/pretty-ts-errors",
    "stargazers_count": 11741,
    "open_issues_count": 16,
    "forks_count": 82
  },
  {
    "full_name": "BlockchainCommons/Learning-Bitcoin-from-the-Command-Line",
    "stargazers_count": 2837,
    "open_issues_count": 18,
    "forks_count": 686
  },
  {
    "full_name": "joe-bell/cva",
    "stargazers_count": 4469,
    "open_issues_count": 2,
    "forks_count": 89
  },
  {
    "full_name": "bitcoinbook/bitcoinbook",
    "stargazers_count": 21833,
    "open_issues_count": 144,
    "forks_count": 5814
  },
  {
    "full_name": "public-apis/public-apis",
    "stargazers_count": 268799,
    "open_issues_count": 215,
    "forks_count": 30235
  },
  {
    "full_name": "jaredpalmer/awesome-react-render-props",
    "stargazers_count": 1368,
    "open_issues_count": 5,
    "forks_count": 110
  },
  {
    "full_name": "janishar/nodejs-backend-architecture-typescript",
    "stargazers_count": 2441,
    "open_issues_count": 11,
    "forks_count": 624
  },
  {
    "full_name": "derhnyel/debuggy",
    "stargazers_count": 24,
    "open_issues_count": 0,
    "forks_count": 2
  },
  {
    "full_name": "saranshbht/msc-books",
    "stargazers_count": 105,
    "open_issues_count": 0,
    "forks_count": 52
  },
  {
    "full_name": "codecrafters-io/build-your-own-x",
    "stargazers_count": 226460,
    "open_issues_count": 295,
    "forks_count": 21793
  },
  {
    "full_name": "GitSquared/edex-ui",
    "stargazers_count": 39030,
    "open_issues_count": 6,
    "forks_count": 2438
  },
  {
    "full_name": "lohanidamodar/flutter_ui_challenges",
    "stargazers_count": 4388,
    "open_issues_count": 0,
    "forks_count": 1393
  },
  {
    "full_name": "microsoft/frontend-bootcamp",
    "stargazers_count": 10785,
    "open_issues_count": 17,
    "forks_count": 1278
  },
  {
    "full_name": "Abdulqudus001/Abdulqudus001.github.io",
    "stargazers_count": 3,
    "open_issues_count": 0,
    "forks_count": 2
  },
  {
    "full_name": "hoc081098/flutter_validation_login_form_BLoC_pattern_RxDart",
    "stargazers_count": 47,
    "open_issues_count": 8,
    "forks_count": 10
  }
]